LICENSE
MANIFEST.in
NOTICE
README.md
requirements.txt
setup.cfg
setup.py
bzt/__init__.py
bzt/__main__.py
bzt/bza.py
bzt/bzt-configs.json
bzt/cli.py
bzt/environment_helpers.py
bzt/jmx2yaml.py
bzt/linter.py
bzt/requests_model.py
bzt/soapui2yaml.py
bzt/swagger2yaml.py
bzt/utils.py
bzt/engine/__init__.py
bzt/engine/dicts.py
bzt/engine/engine.py
bzt/engine/modules.py
bzt/engine/names.py
bzt/engine/templates.py
bzt/jmx/__init__.py
bzt/jmx/base.py
bzt/jmx/http.py
bzt/jmx/mqtt.py
bzt/jmx/rte.py
bzt/jmx/threadgroups.py
bzt/jmx/tools.py
bzt/modules/__init__.py
bzt/modules/_locustio.py
bzt/modules/_molotov.py
bzt/modules/_pytest.py
bzt/modules/_selenium.py
bzt/modules/ab.py
bzt/modules/aggregator.py
bzt/modules/console.py
bzt/modules/csharp.py
bzt/modules/external.py
bzt/modules/functional.py
bzt/modules/gatling.py
bzt/modules/javascript.py
bzt/modules/jmeter.py
bzt/modules/k6.py
bzt/modules/monitoring.py
bzt/modules/passfail.py
bzt/modules/provisioning.py
bzt/modules/proxy2jmx.py
bzt/modules/reporting.py
bzt/modules/robot.py
bzt/modules/ruby.py
bzt/modules/screen.py
bzt/modules/services.py
bzt/modules/shellexec.py
bzt/modules/siege.py
bzt/modules/soapui.py
bzt/modules/tsung.py
bzt/modules/vegeta.py
bzt/modules/_apiritif/__init__.py
bzt/modules/_apiritif/ast_helpers.py
bzt/modules/_apiritif/executor.py
bzt/modules/_apiritif/generator.py
bzt/modules/_apiritif/jmeter_functions.py
bzt/modules/blazemeter/__init__.py
bzt/modules/blazemeter/blazemeter_reporter.py
bzt/modules/blazemeter/cloud_provisioning.py
bzt/modules/blazemeter/cloud_test.py
bzt/modules/blazemeter/const.py
bzt/modules/blazemeter/net_utils.py
bzt/modules/blazemeter/project_finder.py
bzt/modules/java/__init__.py
bzt/modules/java/executors.py
bzt/modules/java/tools.py
bzt/resources/10-base-config.yml
bzt/resources/__init__.py
bzt/resources/base-bzt-rc.yml
bzt/resources/chrome-loader.c
bzt/resources/chrome_launcher.sh
bzt/resources/locustio-taurus-wrapper.py
bzt/resources/mocha-taurus-plugin.js
bzt_tcps.egg-info/PKG-INFO
bzt_tcps.egg-info/SOURCES.txt
bzt_tcps.egg-info/dependency_links.txt
bzt_tcps.egg-info/entry_points.txt
bzt_tcps.egg-info/requires.txt
bzt_tcps.egg-info/top_level.txt