Metadata-Version: 2.1
Name: bzt-tcps
Version: 0.2
Summary: Taurus Tool for Continuous Testing
Home-page: http://gettaurus.org/
Author: shaonian
Author-email: licetianyr@163.com
License: Apache 2.0
Download-URL: http://gettaurus.org/docs/DeveloperGuide/#Python-Egg-Snapshots
Platform: UNKNOWN
Classifier: Development Status :: 5 - Production/Stable
Classifier: Topic :: Software Development :: Quality Assurance
Classifier: Topic :: Software Development :: Testing
Classifier: Topic :: Software Development :: Testing :: Traffic Generation
Classifier: License :: OSI Approved :: Apache Software License
Classifier: Operating System :: Microsoft :: Windows
Classifier: Operating System :: MacOS
Classifier: Operating System :: POSIX :: Linux
Classifier: Programming Language :: Python :: 3.7
Classifier: Programming Language :: Python :: 3.8
Classifier: Programming Language :: Python :: 3.9
Requires-Python: >=3.6
